typeflow/__init__.py
typeflow/cli/__init__.py
typeflow/cli/commands/__init__.py
typeflow/cli/commands/add.py
typeflow/cli/commands/compile_graph.py
typeflow/cli/commands/create_class.py
typeflow/cli/commands/create_node.py
typeflow/cli/commands/generate.py
typeflow/cli/commands/install.py
typeflow/cli/commands/remove.py
typeflow/cli/commands/run.py
typeflow/cli/commands/setup.py
typeflow/cli/commands/start_ui.py
typeflow/cli/commands/validate/__init__.py
typeflow/cli/commands/validate/app.py
typeflow/cli/commands/validate/utils.py
typeflow/cli/commands/validate/validate_class.py
typeflow/cli/commands/validate/validate_node.py
typeflow/cli/commands/validate/validate_workflow.py
typeflow/cli/main.py
typeflow/cli/template/__init__.py
typeflow/cli/template/class_template.py
typeflow/cli/template/gitignore.py
typeflow/cli/template/node_template.py
typeflow/cli/template/workflow_yaml.py
typeflow/core/__init__.py
typeflow/core/first.py
typeflow/core/script_generator.py
typeflow/sdk/__init__.py
typeflow/sdk/node.py
typeflow/sdk/nodeclass.py
typeflow/server/__init__.py
typeflow/server/core/loader.py
typeflow/server/core/saver.py
typeflow/server/main.py
typeflow/server/routes/__init__.py
typeflow/server/routes/api.py
typeflow/server/routes/ui.py
typeflow/server/utils/__init__.py
typeflow/server/utils/class_json.py
typeflow/server/utils/const_yaml.py
typeflow/server/utils/node_json.py
typeflow/ui/__init__.py
typeflow/ui/build/404.html
typeflow/ui/build/__next.__PAGE__.txt
typeflow/ui/build/__next._full.txt
typeflow/ui/build/__next._index.txt
typeflow/ui/build/__next._tree.txt
typeflow/ui/build/_next/static/chunks/01900ab0d3652a9e.js
typeflow/ui/build/_next/static/chunks/24e37cc8d11d93d2.js
typeflow/ui/build/_next/static/chunks/37881448663c7a5a.js
typeflow/ui/build/_next/static/chunks/42879de7b8087bc9.js
typeflow/ui/build/_next/static/chunks/7a4a1d89b022c184.js
typeflow/ui/build/_next/static/chunks/a6dad97d9634a72d.js
typeflow/ui/build/_next/static/chunks/b07241f96c2a0fe3.js
typeflowapp-0.0.4.dist-info/entry_points.txt
typeflowapp-0.0.4.dist-info/licenses/LICENSE
typeflowapp-0.0.4.dist-info/METADATA
typeflowapp-0.0.4.dist-info/WHEEL
typeflowapp-0.0.4.dist-info/RECORD
