Metadata-Version: 2.4
Name: typeflowapp
Version: 0.0.4
Summary: A visual programming interface for node based programming in python
License: GNU GPLv3
License-File: LICENSE
Author: Sraban Mondal
Author-email: srabanmondal1@gmail.com
Requires-Python: >=3.12
Classifier: License :: Other/Proprietary License
Classifier: Programming Language :: Python :: 3
Classifier: Programming Language :: Python :: 3.12
Classifier: Programming Language :: Python :: 3.13
Classifier: Programming Language :: Python :: 3.14
Requires-Dist: fastapi (>=0.120.4,<0.121.0)
Requires-Dist: numpy (>=2.3.4,<3.0.0)
Requires-Dist: pandas (>=2.3.3,<3.0.0)
Requires-Dist: pillow (>=12.0.0,<13.0.0)
Requires-Dist: pydantic (>=2.12.3,<3.0.0)
Requires-Dist: python-multipart (>=0.0.20,<0.0.21)
Requires-Dist: pyyaml (>=6.0.3,<7.0.0)
Requires-Dist: typer (>=0.19.2,<0.20.0)
Requires-Dist: uv (>=0.9.5,<0.10.0)
Requires-Dist: uvicorn (>=0.38.0,<0.39.0)
